socatlord/__init__.py
socatlord/operations.py
socatlord/parse_config.py
socatlord/run.py
socatlord/systemd/socatlord.service
socatlord-1.3.dist-info/LICENSE
socatlord-1.3.dist-info/METADATA
socatlord-1.3.dist-info/WHEEL
socatlord-1.3.dist-info/entry_points.txt
socatlord-1.3.dist-info/top_level.txt
socatlord-1.3.dist-info/RECORD
