Metadata-Version: 2.1
Name: socatlord
Version: 1.3
Summary: A utility to manage all socats of yours
Home-page: https://github.com/Cervi-Robotics/socatlord
Author: Piotr Maślanka
Author-email: piotr.maslanka@dronehub.ai
License: UNKNOWN
Project-URL: Code, https://github.com/Cervi-Robotics/socatlord
Project-URL: Issue tracker, https://github.com/Cervi-Robotics/socatlord/issues
Keywords: socat,systemd,utility
Platform: UNKNOWN
Classifier: Programming Language :: Python
Classifier: Programming Language :: Python :: 3.5
Classifier: Programming Language :: Python :: 3.6
Classifier: Programming Language :: Python :: 3.7
Classifier: Programming Language :: Python :: 3.8
Classifier: Programming Language :: Python :: 3.9
Classifier: Programming Language :: Python :: Implementation :: CPython
Classifier: Programming Language :: Python :: Implementation :: PyPy
Classifier: Operating System :: POSIX
Classifier: Operating System :: OS Independent
Classifier: Development Status :: 4 - Beta
Classifier: License :: OSI Approved :: MIT License
Requires-Dist: satella
